{
  "db_name": "PostgreSQL",
  "query": "SELECT username, is_nsfw\n            FROM users\n            WHERE\n                username LIKE $1 AND\n                ($2 OR NOT is_nsfw) AND\n                delete_timestamp IS NULL\n            ORDER BY username LIMIT $3",
  "describe": {
    "columns": [
      {
        "ordinal": 0,
        "name": "username",
        "type_info": "Text"
      },
      {
        "ordinal": 1,
        "name": "is_nsfw",
        "type_info": "Bool"
      }
    ],
    "parameters": {
      "Left": [
        "Text",
        "Bool",
        "Int8"
      ]
    },
    "nullable": [
      false,
      false
    ]
  },
  "hash": "8346ce66fc1ed19152594a4077fede324912011d9a0737edcc10a45ee58c08dc"
}
